cfnctl/__init__.py
cfnctl/cfnctl.py
cfnctl/commands/__init__.py
cfnctl/commands/deploy.py
cfnctl/commands/lambda_command.py
cfnctl/lib/__init__.py
cfnctl/lib/bucket.py
test/__init__.py
test/commands/__init__.py
test/commands/deploy.py
test/lib/__init__.py
test/lib/bucket.py
test/mocks/__init__.py
test/mocks/cloudformation.py
test/mocks/s3.py
cfnctl-0.4.5.dist-info/LICENSE
cfnctl-0.4.5.dist-info/METADATA
cfnctl-0.4.5.dist-info/WHEEL
cfnctl-0.4.5.dist-info/entry_points.txt
cfnctl-0.4.5.dist-info/top_level.txt
cfnctl-0.4.5.dist-info/RECORD
