Metadata-Version: 2.1
Name: cfnctl
Version: 0.4.5
Summary: Command line launch and management tool for AWS CloudFormation
Home-page: https://github.com/stelligent/cfnctl
Author: Michael Neil
Author-email: michael.neil@stelligent.com
License: Apache License 2.0
Keywords: aws cfn control cfnctl cloudformation stack stackset
Platform: UNKNOWN
Classifier: Intended Audience :: Developers
Classifier: Natural Language :: English
Classifier: Environment :: Web Environment
Classifier: License :: OSI Approved :: Apache Software License
Classifier: Operating System :: OS Independent
Classifier: Development Status :: 1 - Planning
Classifier: Programming Language :: Python
Classifier: Programming Language :: Python :: 3.7
Classifier: Topic :: Software Development :: Libraries :: Python Modules
Classifier: Topic :: Utilities
Requires-Dist: boto3 (>=1.9.59)
Requires-Dist: jinja2 (>=2.10)
